tasktree/__init__.py
tasktree/cli.py
tasktree/docker.py
tasktree/executor.py
tasktree/graph.py
tasktree/hasher.py
tasktree/parser.py
tasktree/state.py
tasktree/substitution.py
tasktree/types.py
tasktree-0.0.20.dist-info/METADATA
tasktree-0.0.20.dist-info/WHEEL
tasktree-0.0.20.dist-info/entry_points.txt
tasktree-0.0.20.dist-info/RECORD
