Metadata-Version: 2.4
Name: tasktree
Version: 0.0.20
Summary: A task automation tool with incremental execution
Requires-Python: >=3.11
Requires-Dist: click>=8.1.0
Requires-Dist: colorama>=0.4.6
Requires-Dist: pathspec>=0.11.0
Requires-Dist: pyyaml>=6.0
Requires-Dist: rich>=13.0.0
Requires-Dist: typer>=0.9.0
Provides-Extra: dev
Requires-Dist: pytest>=9.0.2; extra == 'dev'
